mailmangler/tests.py
mailmangler/settings.py
mailmangler/__init__.py
django_mailmangler-0.1.0.dist-info/top_level.txt
django_mailmangler-0.1.0.dist-info/METADATA
django_mailmangler-0.1.0.dist-info/DESCRIPTION.rst
django_mailmangler-0.1.0.dist-info/metadata.json
django_mailmangler-0.1.0.dist-info/WHEEL
django_mailmangler-0.1.0.dist-info/RECORD
