Metadata-Version: 2.0
Name: django-mailmangler
Version: 0.1.0
Summary: Template tags to weakly obfuscate an email behind JavaScript or a CAPTCHA (a reCAPTCHA)
Home-page: https://github.com/nicktimko/django-mailmangler
Author: Nick Timkovich
Author-email: prometheus235@gmail.com
License: MIT
Keywords: captcha recaptcha mailhide django
Platform: UNKNOWN
Classifier: Development Status :: 3 - Alpha
Classifier: Environment :: Web Environment
Classifier: Framework :: Django
Classifier: Intended Audience :: Developers
Classifier: License :: OSI Approved :: MIT License
Classifier: Operating System :: OS Independent
Classifier: Programming Language :: Python
Classifier: Programming Language :: Python :: 2
Classifier: Programming Language :: Python :: 2.6
Classifier: Programming Language :: Python :: 2.7
Classifier: Programming Language :: Python :: 3
Requires-Dist: recaptcha-client
Requires-Dist: pycrypto
